{
    "Name":  "IMF.P.Export.JSON.ParentChild",
    "Code@Code.link":  "IMF.P.Export.JSON.ParentChild.ti",
    "Parameters":  [
                       {
                           "Name":  "pPrefix",
                           "Prompt":  "Prefix",
                           "Value":  "IMF"
                       },
                       {
                           "Name":  "pDimensionCode",
                           "Prompt":  "Dimension Code",
                           "Value":  ""
                       },
                       {
                           "Name":  "pVersionId",
                           "Prompt":  "Version Id",
                           "Value":  ""
                       },
                       {
                           "Name":  "pFilePath",
                           "Prompt":  "File Path",
                           "Value":  ""
                       }
                   ]
}
